Metadata-Version: 1.0
Name: jb-probablity
Version: 0.1
Summary: Gaussian and Binomial distributions
Home-page: UNKNOWN
Author: Jay Bagrecha
Author-email: UNKNOWN
License: UNKNOWN
Platform: UNKNOWN
